odoo/addons/shopfloor_mobile/README.rst
odoo/addons/shopfloor_mobile/__init__.py
odoo/addons/shopfloor_mobile/__manifest__.py
odoo/addons/shopfloor_mobile/i18n/es_AR.po
odoo/addons/shopfloor_mobile/i18n/it.po
odoo/addons/shopfloor_mobile/i18n/pt_BR.po
odoo/addons/shopfloor_mobile/i18n/shopfloor_mobile.pot
odoo/addons/shopfloor_mobile/migrations/14.0.1.1.0/post-migrate.py
odoo/addons/shopfloor_mobile/readme/CONTRIBUTORS.rst
odoo/addons/shopfloor_mobile/readme/CREDITS.rst
odoo/addons/shopfloor_mobile/readme/DESCRIPTION.rst
odoo/addons/shopfloor_mobile/readme/HISTORY.rst
odoo/addons/shopfloor_mobile/readme/ROADMAP.rst
odoo/addons/shopfloor_mobile/readme/USAGE.rst
odoo/addons/shopfloor_mobile/static/description/icon.png
odoo/addons/shopfloor_mobile/static/description/index.html
odoo/addons/shopfloor_mobile/static/wms/.gitignore
odoo/addons/shopfloor_mobile/static/wms/src/screen.js
odoo/addons/shopfloor_mobile/static/wms/src/wms_utils.js
odoo/addons/shopfloor_mobile/static/wms/src/components/batch_picking_detail.js
odoo/addons/shopfloor_mobile/static/wms/src/components/batch_picking_line_detail.js
odoo/addons/shopfloor_mobile/static/wms/src/components/manual_select_color.js
odoo/addons/shopfloor_mobile/static/wms/src/components/misc.js
odoo/addons/shopfloor_mobile/static/wms/src/components/packaging-qty-picker.js
odoo/addons/shopfloor_mobile/static/wms/src/components/detail/detail_location.js
odoo/addons/shopfloor_mobile/static/wms/src/components/detail/detail_lot.js
odoo/addons/shopfloor_mobile/static/wms/src/components/detail/detail_operation.js
odoo/addons/shopfloor_mobile/static/wms/src/components/detail/detail_package.js
odoo/addons/shopfloor_mobile/static/wms/src/components/detail/detail_picking.js
odoo/addons/shopfloor_mobile/static/wms/src/components/detail/detail_product.js
odoo/addons/shopfloor_mobile/static/wms/src/components/detail/detail_transfer.js
odoo/addons/shopfloor_mobile/static/wms/src/components/forms/form_edit_stock_picking.js
odoo14_addon_shopfloor_mobile-14.0.1.39.0.dist-info/METADATA
odoo14_addon_shopfloor_mobile-14.0.1.39.0.dist-info/WHEEL
odoo14_addon_shopfloor_mobile-14.0.1.39.0.dist-info/top_level.txt
odoo14_addon_shopfloor_mobile-14.0.1.39.0.dist-info/RECORD
